mcp_f1analisys/__init__.py
mcp_f1analisys/__main__.py
mcp_f1analisys/_version.py
mcp_f1analisys/server.py
mcp_f1analisys-0.1.6.dist-info/licenses/LICENSE
mcp_f1analisys-0.1.6.dist-info/METADATA
mcp_f1analisys-0.1.6.dist-info/WHEEL
mcp_f1analisys-0.1.6.dist-info/entry_points.txt
mcp_f1analisys-0.1.6.dist-info/top_level.txt
mcp_f1analisys-0.1.6.dist-info/RECORD
