Metadata-Version: 2.4
Name: mcp-f1analisys
Version: 0.1.6
Summary: MCP F1 analysis
Author-email: Maxbleu <juanfranciscomm03@gmail.com>
License: MIT License
Project-URL: Homepage, https://github.com/maxbleu/mcp-f1analisys
Classifier: Programming Language :: Python :: 3
Classifier: License :: OSI Approved :: MIT License
Requires-Python: >=3.12
License-File: LICENSE
Requires-Dist: mcp[cli]>=1.0.0
Requires-Dist: httpx>=0.24.0
Dynamic: license-file
